LICENSE
README.md
pyproject.toml
pipa/__about__.py
pipa/__init__.py
pipa/main.py
pipa/analysis/__init__.py
pipa/analysis/export/csv.py
pipa/analysis/flamegraph/__init__.py
pipa/analysis/flamegraph/analyzer.py
pipa/analysis/flamegraph/api.py
pipa/analysis/flamegraph/io.py
pipa/analysis/flamegraph/trie.py
pipa/common/__init__.py
pipa/common/cmd.py
pipa/common/config.py
pipa/common/export.py
pipa/common/logger.py
pipa/common/utils.py
pipa/common/hardware/cpu.py
pipa/parser/__init__.py
pipa/parser/perf_buildid.py
pipa/parser/perf_report.py
pipa/parser/perf_script.py
pipa/parser/perf_script_call.py
pipa/parser/perf_stat.py
pipa/parser/flamegraph/stackcollapse_perf.py
pipa/parser/sar/sadf.py
pipa/parser/sar/sar.py
pipa/parser/sar/sar_index.py
pipa/parser/sar/sar_parser.py
pipa/parser/sar/sar_plotter.py
pipa/parser/sar/sar_processor.py
pipa/scripts/__init__.py
pipa/scripts/perf_sqlite.py
pipa/service/__init__.py
pipa/service/archive.py
pipa/service/download.py
pipa/service/dump.py
pipa/service/export_sys_config.py
pipa/service/init.py
pipa/service/pipashu.py
pipa/service/remote.py
pipa/service/upload.py
pipa/service/call_graph/__init__.py
pipa/service/call_graph/addr.py
pipa/service/call_graph/call_graph.py
pipa/service/call_graph/func_node.py
pipa/service/call_graph/node.py
pipa/service/gengerate/all.py
pipa/service/gengerate/export_pipashu_config_template.py
pipa/service/gengerate/parse_pipashu_config.py
pipa/service/gengerate/run_by_pipa.py
pipa/service/gengerate/run_by_user.py
pipa/service/gengerate/utils.py
pipa/service/gengerate/common/collect.py
pipa/service/pipad/.gitignore
pipa/service/pipad/Makefile
pipa/service/pipad/__init__.py
pipa/service/pipad/pipad.proto
pipa/service/pipad/pipad_client.py
pipa/service/pipad/pipad_pb2.py
pipa/service/pipad/pipad_pb2.pyi
pipa/service/pipad/pipad_pb2_grpc.py
pipa/service/pipad/pipad_server.py
pypipa-0.0.18.dist-info/METADATA
pypipa-0.0.18.dist-info/WHEEL
pypipa-0.0.18.dist-info/entry_points.txt
pypipa-0.0.18.dist-info/licenses/LICENSE
pypipa-0.0.18.dist-info/RECORD
