Metadata-Version: 2.4
Name: pypipa
Version: 0.0.18
Summary: Platform Integrated Performance Analytics, PIPA
Project-URL: Documentation, https://github.com/ZJU-SPAIL/pipa#readme
Project-URL: Issues, https://github.com/ZJU-SPAIL/pipa/issues
Project-URL: Source, https://github.com/ZJU-SPAIL/pipa
Author-email: Benard Jiang <bernardjiang5@outlook.com>
License-Expression: MIT
License-File: LICENSE
Keywords: analytics,integrated,observability,performance,pipa,platform
Classifier: Development Status :: 3 - Alpha
Classifier: Operating System :: POSIX :: Linux
Classifier: Programming Language :: Python
Classifier: Programming Language :: Python :: 3.10
Classifier: Programming Language :: Python :: 3.11
Classifier: Programming Language :: Python :: 3.12
Classifier: Programming Language :: Python :: 3.13
Classifier: Programming Language :: Python :: Implementation :: CPython
Classifier: Programming Language :: Python :: Implementation :: PyPy
Classifier: Topic :: System :: Monitoring
Requires-Python: >=3.10
Requires-Dist: capstone
Requires-Dist: fire>=0.6.0
Requires-Dist: grpcio
Requires-Dist: matplotlib
Requires-Dist: nbformat
Requires-Dist: networkx
Requires-Dist: pandarallel
Requires-Dist: pandas>=2.2.2
Requires-Dist: paramiko
Requires-Dist: plotly
Requires-Dist: protobuf
Requires-Dist: psutil
Requires-Dist: pydot
Requires-Dist: pyelftools
Requires-Dist: pyyaml>=6.0.1
Requires-Dist: questionary>=2.0.1
Requires-Dist: requests
Requires-Dist: rich>=13.7.1
Requires-Dist: scipy
Requires-Dist: seaborn
Provides-Extra: dev
Requires-Dist: black; extra == 'dev'
Requires-Dist: build; extra == 'dev'
Requires-Dist: flake8; extra == 'dev'
Requires-Dist: grpcio-tools; extra == 'dev'
Requires-Dist: pytest; extra == 'dev'
